cogentic/__init__.py
cogentic/orchestration/__init__.py
cogentic/orchestration/chat.py
cogentic/orchestration/model_output.py
cogentic/orchestration/orchestrator.py
cogentic/orchestration/models/action.py
cogentic/orchestration/models/artifact.py
cogentic/orchestration/models/base.py
cogentic/orchestration/models/evidence.py
cogentic/orchestration/models/hypothesis.py
cogentic/orchestration/models/issue.py
cogentic/orchestration/models/ledger.py
cogentic/orchestration/models/orchestration.py
cogentic/orchestration/models/plan.py
cogentic/orchestration/models/reasoning.py
cogentic/orchestration/models/state.py
cogentic/orchestration/models/test.py
cogentic/orchestration/prompts/__init__.py
cogentic/orchestration/prompts/create_progress_ledger.md
cogentic/orchestration/prompts/current_state.md
cogentic/orchestration/prompts/final_answer.md
cogentic/orchestration/prompts/initial_evidence.md
cogentic/orchestration/prompts/initial_hypotheses.md
cogentic/orchestration/prompts/next_step.md
cogentic/orchestration/prompts/persona.md
cogentic/orchestration/prompts/prompts.py
cogentic/orchestration/prompts/summarize_result.md
cogentic/orchestration/prompts/update_hypothesis.md
cogentic/orchestration/prompts/update_hypothesis_on_stall.md
cogentic/orchestration/prompts/update_plan.md
cogentic/orchestration/prompts/update_plan_on_stall.md
cogentic-0.1.7.dist-info/METADATA
cogentic-0.1.7.dist-info/WHEEL
cogentic-0.1.7.dist-info/licenses/LICENSE
cogentic-0.1.7.dist-info/RECORD
