Metadata-Version: 2.4
Name: cogentic
Version: 0.1.7
Summary: A hypothesis-based orchestration framework built on AutoGen and based on MagenticOne
Project-URL: homepage, https://github.com/knifeyspoony/cogentic
Project-URL: issues, https://github.com/knifeyspoony/cogentic/issues
Author: knifeyspoony
License: MIT License
License-File: LICENSE
Keywords: agents,ai,autogen,llm,orchestration
Classifier: Development Status :: 3 - Alpha
Classifier: Intended Audience :: Developers
Classifier: Intended Audience :: Science/Research
Classifier: Operating System :: OS Independent
Classifier: Programming Language :: Python :: 3.12
Classifier: Programming Language :: Python :: 3.13
Requires-Python: >=3.12
Requires-Dist: autogen-agentchat>=0.4.7
